<pragmas>
<pragma file="C:/Xilinx/Vitis_HLS/2023.1/common/technology/autopilot\etc/ap_common.h" line="523" pragmaType="inline" parentfunction="_ZN8ssdm_intILi1ELb0EEC2EDq1_j" off="0" region="0" recursive="0"/>
<pragma file="C:/Xilinx/Vitis_HLS/2023.1/common/technology/autopilot\etc/ap_common.h" line="523" pragmaType="inline" parentfunction="ssdm_int<32, false>::ssdm_int(unsigned int)" off="0" region="0" recursive="0"/>
<pragma file="" line="0" pragmaType="inline" parentfunction="ap_int<33>::ap_int<33, true>(ap_int_base<33, true> const&)" off="0" region="0" recursive="0"/>
<pragma file="C:/Xilinx/Vitis_HLS/2023.1/common/technology/autopilot\etc/ap_common.h" line="515" pragmaType="inline" parentfunction="_ZN8ssdm_intILi33ELb1EEC2EDq33_i" off="0" region="0" recursive="0"/>
<pragma file="../ip_repo/aes128_hls/src/AES_Encrypt.cpp" line="138" pragmaType="pipeline" parentfunction="MixSingleColumn" off="0" ii="-1" rewind="0" style=""/>
<pragma file="" line="0" pragmaType="inline" parentfunction="ap_range_ref<8, true>::ap_range_ref(ap_int_base<8, true>*, int, int)" off="0" region="0" recursive="0"/>
<pragma file="" line="0" pragmaType="inline" parentfunction="range" off="0" region="0" recursive="0"/>
<pragma file="../ip_repo/aes128_hls/src/AES_Encrypt.cpp" line="208" pragmaType="unroll" parentfunction="AES128Encrypt" factor="-1" skip_exit_check="0"/>
<pragma file="../ip_repo/aes128_hls/src/AES_Encrypt.cpp" line="195" pragmaType="pipeline" parentfunction="AES128Encrypt" off="0" ii="-1" rewind="0" style=""/>
<pragma file="../ip_repo/aes128_hls/src/AES_Encrypt.cpp" line="187" pragmaType="unroll" parentfunction="AES128Encrypt" factor="-1" skip_exit_check="0"/>
<pragma file="../ip_repo/aes128_hls/src/AES_Encrypt.cpp" line="169" pragmaType="interface" parentfunction="AES128Encrypt" mode="m_axi" port="key" bundle="data" offset="slave" name="" depth="16" num_read_outstanding="-1" num_write_outstanding="-1" max_burst_read_length="-1" max_burst_write_length="-1" latency="-1" max_widen_bitwidth="-1" channel=""/>
<pragma file="../ip_repo/aes128_hls/src/AES_Encrypt.cpp" line="170" pragmaType="interface" parentfunction="AES128Encrypt" mode="m_axi" port="plaintext" bundle="data" offset="slave" name="" depth="16" num_read_outstanding="-1" num_write_outstanding="-1" max_burst_read_length="-1" max_burst_write_length="-1" latency="-1" max_widen_bitwidth="-1" channel=""/>
<pragma file="../ip_repo/aes128_hls/src/AES_Encrypt.cpp" line="171" pragmaType="interface" parentfunction="AES128Encrypt" mode="m_axi" port="ciphertext" bundle="data" offset="slave" name="" depth="16" num_read_outstanding="-1" num_write_outstanding="-1" max_burst_read_length="-1" max_burst_write_length="-1" latency="-1" max_widen_bitwidth="-1" channel=""/>
<pragma file="../ip_repo/aes128_hls/src/AES_Encrypt.cpp" line="182" pragmaType="array_partition" parentfunction="AES128Encrypt" dim="1" factor="0" mode="complete" dynamic="0" variable="state"/>
<pragma file="../ip_repo/aes128_hls/src/AES_Encrypt.cpp" line="183" pragmaType="array_partition" parentfunction="AES128Encrypt" dim="1" factor="0" mode="complete" dynamic="0" variable="scheduled_key"/>
<pragma file="" line="0" pragmaType="inline" parentfunction="get" off="0" region="0" recursive="0"/>
<pragma file="" line="0" pragmaType="inline" parentfunction="ap_int_base<33, true>::ap_int_base(int)" off="0" region="0" recursive="0"/>
<pragma file="../ip_repo/aes128_hls/src/AES_Encrypt.cpp" line="150" pragmaType="inline" parentfunction="MixColumns" off="0" region="0" recursive="1"/>
<pragma file="../ip_repo/aes128_hls/src/AES_Encrypt.cpp" line="161" pragmaType="unroll" parentfunction="MixColumns" factor="-1" skip_exit_check="0"/>
<pragma file="../ip_repo/aes128_hls/src/AES_Encrypt.cpp" line="157" pragmaType="unroll" parentfunction="MixColumns" factor="-1" skip_exit_check="0"/>
<pragma file="../ip_repo/aes128_hls/src/AES_Encrypt.cpp" line="152" pragmaType="array_partition" parentfunction="MixColumns" dim="1" factor="0" mode="complete" dynamic="0" variable="next_state"/>
<pragma file="" line="0" pragmaType="inline" parentfunction="ap_int_base<8, false>::ap_int_base()" off="0" region="0" recursive="0"/>
<pragma file="../ip_repo/aes128_hls/src/AES_Encrypt.cpp" line="117" pragmaType="unroll" parentfunction="ShiftRows" factor="-1" skip_exit_check="0"/>
<pragma file="../ip_repo/aes128_hls/src/AES_Encrypt.cpp" line="83" pragmaType="array_partition" parentfunction="ShiftRows" dim="1" factor="0" mode="complete" dynamic="0" variable="next_state"/>
<pragma file="" line="0" pragmaType="inline" parentfunction="to_uint" off="0" region="0" recursive="0"/>
<pragma file="" line="0" pragmaType="inline" parentfunction="ap_uint<8>::ap_uint<8, false>(ap_int_base<8, false> const&)" off="0" region="0" recursive="0"/>
<pragma file="" line="0" pragmaType="inline" parentfunction="ap_int_base<8, false>::ap_int_base<8, true>(ap_range_ref<8, true> const&)" off="0" region="0" recursive="0"/>
<pragma file="" line="0" pragmaType="inline" parentfunction="ap_int_base<1, false>::RType<32, true>::minus operator-<1, false, 32, true>(ap_int_base<1, false> const&, ap_int_base<32, true> const&)" off="0" region="0" recursive="0"/>
<pragma file="" line="0" pragmaType="inline" parentfunction="ap_concat_ref<2, ap_int_base<2, true>, 2, ap_int_base<2, true> >::ap_concat_ref(ap_int_base<2, true>&, ap_int_base<2, true>&)" off="0" region="0" recursive="0"/>
<pragma file="" line="0" pragmaType="inline" parentfunction="ap_int_base<1, false>::ap_int_base(int)" off="0" region="0" recursive="0"/>
<pragma file="../ip_repo/aes128_hls/src/AES_Encrypt.cpp" line="68" pragmaType="unroll" parentfunction="KeyExpansion" factor="-1" skip_exit_check="0"/>
<pragma file="../ip_repo/aes128_hls/src/AES_Encrypt.cpp" line="62" pragmaType="unroll" parentfunction="KeyExpansion" factor="-1" skip_exit_check="0"/>
<pragma file="../ip_repo/aes128_hls/src/AES_Encrypt.cpp" line="46" pragmaType="unroll" parentfunction="KeyExpansion" factor="-1" skip_exit_check="0"/>
<pragma file="../ip_repo/aes128_hls/src/AES_Encrypt.cpp" line="40" pragmaType="array_partition" parentfunction="KeyExpansion" dim="1" factor="0" mode="complete" dynamic="0" variable="expanded_key"/>
<pragma file="../ip_repo/aes128_hls/src/AES_Encrypt.cpp" line="41" pragmaType="array_partition" parentfunction="KeyExpansion" dim="1" factor="0" mode="complete" dynamic="0" variable="subbytes_key"/>
<pragma file="" line="0" pragmaType="inline" parentfunction="ap_int_base<33, true>::ap_int_base<1, false>(ap_int_base<1, false> const&)" off="0" region="0" recursive="0"/>
<pragma file="" line="0" pragmaType="inline" parentfunction="ap_int_base<2, false>::ap_int_base()" off="0" region="0" recursive="0"/>
<pragma file="" line="0" pragmaType="inline" parentfunction="ap_int_base<8, false>::RType<($_0)32, true>::arg1 operator<<<8, true>(ap_range_ref<8, true> const&, int)" off="0" region="0" recursive="0"/>
<pragma file="" line="0" pragmaType="inline" parentfunction="ap_int_base<32, false>::ap_int_base<32, true>(ap_int_base<32, true> const&)" off="0" region="0" recursive="0"/>
<pragma file="" line="0" pragmaType="inline" parentfunction="ap_uint<8> ap_int_base<8, false>::operator>><32>(ap_int_base<32, false> const&) const" off="0" region="0" recursive="0"/>
<pragma file="" line="0" pragmaType="inline" parentfunction="ap_int<4>::ap_int<4, true>(ap_int_base<4, true> const&)" off="0" region="0" recursive="0"/>
<pragma file="" line="0" pragmaType="inline" parentfunction="ap_int_base<8, true>::ap_int_base(unsigned char)" off="0" region="0" recursive="0"/>
<pragma file="" line="0" pragmaType="inline" parentfunction="ap_bit_ref<8, true>::operator bool() const" off="0" region="0" recursive="0"/>
<pragma file="" line="0" pragmaType="inline" parentfunction="ap_int_base<32, true>::operator-() const" off="0" region="0" recursive="0"/>
<pragma file="" line="0" pragmaType="inline" parentfunction="ap_int_base<8, false>::ap_int_base(unsigned char)" off="0" region="0" recursive="0"/>
<pragma file="" line="0" pragmaType="inline" parentfunction="ap_int_base<33, true>::ap_int_base<32, true>(ap_int_base<32, true> const&)" off="0" region="0" recursive="0"/>
<pragma file="" line="0" pragmaType="inline" parentfunction="ap_int_base<2, true>::ap_int_base()" off="0" region="0" recursive="0"/>
<pragma file="C:/Xilinx/Vitis_HLS/2023.1/common/technology/autopilot\etc/ap_common.h" line="515" pragmaType="inline" parentfunction="_ZN8ssdm_intILi4ELb1EEC2EDq4_i" off="0" region="0" recursive="0"/>
<pragma file="" line="0" pragmaType="inline" parentfunction="ap_int<2>::ap_int<2, true>(ap_int_base<2, true> const&)" off="0" region="0" recursive="0"/>
<pragma file="../ip_repo/aes128_hls/src/AES_Encrypt.cpp" line="31" pragmaType="unroll" parentfunction="AddRoundKey" factor="-1" skip_exit_check="0"/>
<pragma file="" line="0" pragmaType="inline" parentfunction="ap_int_base<4, false>::ap_int_base()" off="0" region="0" recursive="0"/>
<pragma file="" line="0" pragmaType="inline" parentfunction="ap_int_base<8, true>::operator()(int, int)" off="0" region="0" recursive="0"/>
<pragma file="" line="0" pragmaType="inline" parentfunction="ap_int<8>::ap_int<8>(ap_uint<8> const&)" off="0" region="0" recursive="0"/>
<pragma file="" line="0" pragmaType="inline" parentfunction="ap_int_base<2, true>::ap_int_base(int)" off="0" region="0" recursive="0"/>
<pragma file="C:/Xilinx/Vitis_HLS/2023.1/common/technology/autopilot\etc/ap_common.h" line="515" pragmaType="inline" parentfunction="_ZN8ssdm_intILi2ELb1EEC2EDq2_i" off="0" region="0" recursive="0"/>
<pragma file="" line="0" pragmaType="inline" parentfunction="set" off="0" region="0" recursive="0"/>
<pragma file="" line="0" pragmaType="inline" parentfunction="ap_int_base<4, true>::ap_int_base(int)" off="0" region="0" recursive="0"/>
<pragma file="" line="0" pragmaType="inline" parentfunction="ap_int_base<8, false>::ap_int_base<8, true>(ap_int_base<8, true> const&)" off="0" region="0" recursive="0"/>
<pragma file="" line="0" pragmaType="inline" parentfunction="set" off="0" region="0" recursive="0"/>
<pragma file="" line="0" pragmaType="inline" parentfunction="ap_int_base<8, true>::ap_int_base<8, false>(ap_int_base<8, false> const&)" off="0" region="0" recursive="0"/>
<pragma file="" line="0" pragmaType="inline" parentfunction="ap_int_base<4, true>::ap_int_base()" off="0" region="0" recursive="0"/>
<pragma file="" line="0" pragmaType="inline" parentfunction="ap_uint<8> ap_int_base<8, false>::operator<<<32>(ap_int_base<32, true> const&) const" off="0" region="0" recursive="0"/>
<pragma file="" line="0" pragmaType="inline" parentfunction="ap_uint<8> ap_int_base<8, false>::operator<<<32>(ap_int_base<32, false> const&) const" off="0" region="0" recursive="0"/>
<pragma file="" line="0" pragmaType="inline" parentfunction="ap_int_base<2, false>::ap_int_base<2, true>(ap_int_base<2, true> const&)" off="0" region="0" recursive="0"/>
<pragma file="" line="0" pragmaType="inline" parentfunction="ap_int_base<2, true>::operator[](int)" off="0" region="0" recursive="0"/>
<pragma file="" line="0" pragmaType="inline" parentfunction="ap_int_base<2, true>::RType<2, true>::logic operator^<2, true, 2, true>(ap_int_base<2, true> const&, ap_int_base<2, true> const&)" off="0" region="0" recursive="0"/>
<pragma file="" line="0" pragmaType="inline" parentfunction="ap_int<4>::ap_int<2, ap_int_base<2, true>, 2, ap_int_base<2, true> >(ap_concat_ref<2, ap_int_base<2, true>, 2, ap_int_base<2, true> > const&)" off="0" region="0" recursive="0"/>
<pragma file="C:/Xilinx/Vitis_HLS/2023.1/common/technology/autopilot\etc/ap_common.h" line="515" pragmaType="inline" parentfunction="ssdm_int<32, true>::ssdm_int(int)" off="0" region="0" recursive="0"/>
<pragma file="" line="0" pragmaType="inline" parentfunction="ap_int_base<32, true>::ap_int_base<8, true>(ap_int_base<8, true> const&)" off="0" region="0" recursive="0"/>
<pragma file="" line="0" pragmaType="inline" parentfunction="ap_int<8>::ap_int<8, true>(ap_int_base<8, true> const&)" off="0" region="0" recursive="0"/>
<pragma file="" line="0" pragmaType="inline" parentfunction="ap_int_base<4, true>::ap_int_base<2, ap_int_base<2, true>, 2, ap_int_base<2, true> >(ap_concat_ref<2, ap_int_base<2, true>, 2, ap_int_base<2, true> > const&)" off="0" region="0" recursive="0"/>
<pragma file="C:/Xilinx/Vitis_HLS/2023.1/common/technology/autopilot\etc/ap_common.h" line="523" pragmaType="inline" parentfunction="_ZN8ssdm_intILi2ELb0EEC2EDq2_j" off="0" region="0" recursive="0"/>
<pragma file="" line="0" pragmaType="inline" parentfunction="ap_int_base<8, true>::ap_int_base()" off="0" region="0" recursive="0"/>
<pragma file="" line="0" pragmaType="inline" parentfunction="ap_int_base<8, false>::ap_int_base(int)" off="0" region="0" recursive="0"/>
<pragma file="" line="0" pragmaType="inline" parentfunction="ap_concat_ref<4, ap_int_base<4, true>, 4, ap_int_base<4, true> >::ap_concat_ref(ap_int_base<4, true>&, ap_int_base<4, true>&)" off="0" region="0" recursive="0"/>
<pragma file="" line="0" pragmaType="inline" parentfunction="ap_int<2>::ap_int()" off="0" region="0" recursive="0"/>
<pragma file="" line="0" pragmaType="inline" parentfunction="ap_concat_ref<2, ap_int_base<2, true>, 2, ap_int_base<2, true> > ap_int_base<2, true>::operator,<2, true>(ap_int_base<2, true>&)" off="0" region="0" recursive="0"/>
<pragma file="" line="0" pragmaType="inline" parentfunction="ap_bit_ref<8, true>::ap_bit_ref(ap_int_base<8, true>*, int)" off="0" region="0" recursive="0"/>
<pragma file="" line="0" pragmaType="inline" parentfunction="get" off="0" region="0" recursive="0"/>
<pragma file="" line="0" pragmaType="inline" parentfunction="ap_int_base<8, true>::ap_int_base<32, true>(ap_int_base<32, true> const&)" off="0" region="0" recursive="0"/>
<pragma file="" line="0" pragmaType="inline" parentfunction="ap_int<32>::ap_int<32, true>(ap_int_base<32, true> const&)" off="0" region="0" recursive="0"/>
<pragma file="C:/Xilinx/Vitis_HLS/2023.1/common/technology/autopilot\etc/ap_common.h" line="523" pragmaType="inline" parentfunction="_ZN8ssdm_intILi4ELb0EEC2EDq4_j" off="0" region="0" recursive="0"/>
<pragma file="" line="0" pragmaType="inline" parentfunction="ap_bit_ref<2, true>::ap_bit_ref(ap_int_base<2, true>*, int)" off="0" region="0" recursive="0"/>
<pragma file="" line="0" pragmaType="inline" parentfunction="ap_int_base<32, true>::ap_int_base(int)" off="0" region="0" recursive="0"/>
<pragma file="" line="0" pragmaType="inline" parentfunction="ap_int_base<4, false>::ap_int_base<4, true>(ap_int_base<4, true> const&)" off="0" region="0" recursive="0"/>
<pragma file="" line="0" pragmaType="inline" parentfunction="ap_int_base<4, true>::operator[](int)" off="0" region="0" recursive="0"/>
<pragma file="" line="0" pragmaType="inline" parentfunction="get" off="0" region="0" recursive="0"/>
<pragma file="" line="0" pragmaType="inline" parentfunction="ap_bit_ref<4, true>::operator bool() const" off="0" region="0" recursive="0"/>
<pragma file="" line="0" pragmaType="inline" parentfunction="ap_bit_ref<4, true>::ap_bit_ref(ap_int_base<4, true>*, int)" off="0" region="0" recursive="0"/>
<pragma file="" line="0" pragmaType="inline" parentfunction="ap_int_base<4, false>::ap_int_base(int)" off="0" region="0" recursive="0"/>
<pragma file="" line="0" pragmaType="inline" parentfunction="ap_int_base<8, true>::ap_int_base<4, ap_int_base<4, true>, 4, ap_int_base<4, true> >(ap_concat_ref<4, ap_int_base<4, true>, 4, ap_int_base<4, true> > const&)" off="0" region="0" recursive="0"/>
<pragma file="" line="0" pragmaType="inline" parentfunction="ap_bit_ref<2, true>::operator bool() const" off="0" region="0" recursive="0"/>
<pragma file="C:/Xilinx/Vitis_HLS/2023.1/common/technology/autopilot\etc/ap_common.h" line="523" pragmaType="inline" parentfunction="ssdm_int<8, false>::ssdm_int(unsigned char)" off="0" region="0" recursive="0"/>
<pragma file="" line="0" pragmaType="inline" parentfunction="ap_int_base<8, true>::RType<32, true>::logic operator^<8, true, 32, true>(ap_int_base<8, true> const&, ap_int_base<32, true> const&)" off="0" region="0" recursive="0"/>
<pragma file="" line="0" pragmaType="inline" parentfunction="ap_int_base<8, true>::ap_int_base(int)" off="0" region="0" recursive="0"/>
<pragma file="" line="0" pragmaType="inline" parentfunction="ap_int<8>::ap_int(unsigned char)" off="0" region="0" recursive="0"/>
<pragma file="" line="0" pragmaType="inline" parentfunction="ap_concat_ref<4, ap_int_base<4, true>, 4, ap_int_base<4, true> > ap_int_base<4, true>::operator,<4, true>(ap_int_base<4, true>&)" off="0" region="0" recursive="0"/>
<pragma file="../ip_repo/aes128_hls/src/Sbox_Composite.cpp" line="74" pragmaType="unroll" parentfunction="gf8_isomorphic_map" factor="-1" skip_exit_check="0"/>
<pragma file="" line="0" pragmaType="inline" parentfunction="ap_int<8>::ap_int(int)" off="0" region="0" recursive="0"/>
<pragma file="" line="0" pragmaType="inline" parentfunction="ap_int<8>::ap_int<4, ap_int_base<4, true>, 4, ap_int_base<4, true> >(ap_concat_ref<4, ap_int_base<4, true>, 4, ap_int_base<4, true> > const&)" off="0" region="0" recursive="0"/>
<pragma file="" line="0" pragmaType="inline" parentfunction="ap_int_base<4, true>::RType<4, true>::logic operator^<4, true, 4, true>(ap_int_base<4, true> const&, ap_int_base<4, true> const&)" off="0" region="0" recursive="0"/>
<pragma file="C:/Xilinx/Vitis_HLS/2023.1/common/technology/autopilot\etc/ap_common.h" line="515" pragmaType="inline" parentfunction="ssdm_int<8, true>::ssdm_int(signed char)" off="0" region="0" recursive="0"/>
<pragma file="" line="0" pragmaType="inline" parentfunction="ap_int<4>::ap_int()" off="0" region="0" recursive="0"/>
<pragma file="../ip_repo/aes128_hls/src/Sbox_Composite.cpp" line="84" pragmaType="unroll" parentfunction="gf8_inv_isomorphic_map" factor="-1" skip_exit_check="0"/>
<pragma file="../ip_repo/aes128_hls/src/AES_Encrypt.cpp" line="22" pragmaType="unroll" parentfunction="SubBytes" factor="-1" skip_exit_check="0"/>
<pragma file="../ip_repo/aes128_hls/src/Sbox_Composite.cpp" line="116" pragmaType="unroll" parentfunction="affine_transform" factor="-1" skip_exit_check="0"/>
<pragma file="" line="0" pragmaType="inline" parentfunction="ap_int<8>::ap_int()" off="0" region="0" recursive="0"/>
<pragma file="" line="0" pragmaType="inline" parentfunction="xor_reduce" off="0" region="0" recursive="0"/>
<pragma file="" line="0" pragmaType="inline" parentfunction="ap_int_base<8, true>::operator[](int)" off="0" region="0" recursive="0"/>
<pragma file="" line="0" pragmaType="inline" parentfunction="ap_int_base<8, true>::RType<($_0)32, true>::logic operator^<8, true>(ap_int_base<8, true> const&, int)" off="0" region="0" recursive="0"/>
<pragma file="" line="0" pragmaType="inline" parentfunction="ap_concat_ref<4, ap_int_base<4, true>, 4, ap_int_base<4, true> > ap_int_base<4, true>::operator,<4, true>(ap_int_base<4, true> const&)" off="0" region="0" recursive="0"/>
<pragma file="" line="0" pragmaType="inline" parentfunction="ap_int_base<8, true>::operator long long() const" off="0" region="0" recursive="0"/>
<pragma file="" line="0" pragmaType="inline" parentfunction="ap_int_base<8, true>::RType<8, true>::logic operator&<8, true, 8, true>(ap_int_base<8, true> const&, ap_int_base<8, true> const&)" off="0" region="0" recursive="0"/>
<pragma file="../ip_repo/aes128_hls/src/Sbox_Composite.cpp" line="165" pragmaType="inline" parentfunction="Sbox" off="0" region="0" recursive="1"/>
<pragma file="" line="0" pragmaType="inline" parentfunction="ap_int<8>::ap_int<32>(ap_int<32> const&)" off="0" region="0" recursive="0"/>
<pragma file="" line="0" pragmaType="inline" parentfunction="length" off="0" region="0" recursive="0"/>
<pragma file="" line="0" pragmaType="inline" parentfunction="ap_int_base<32, false>& ap_int_base<32, false>::operator=<33, true>(ap_int_base<33, true> const&)" off="0" region="0" recursive="0"/>
<pragma file="C:/Xilinx/Vitis_HLS/2023.1/common/technology/autopilot\etc/ap_common.h" line="0" pragmaType="inline" parentfunction="ssdm_int<8, false>::ssdm_int()" off="0" region="0" recursive="0"/>
<pragma file="" line="0" pragmaType="inline" parentfunction="checkOverflowBaseC" off="0" region="0" recursive="0"/>
<pragma file="" line="0" pragmaType="inline" parentfunction="ap_bit_ref<2, true>::operator=(int)" off="0" region="0" recursive="0"/>
<pragma file="" line="0" pragmaType="inline" parentfunction="ap_bit_ref<4, true>::operator=(unsigned long long)" off="0" region="0" recursive="0"/>
<pragma file="" line="0" pragmaType="inline" parentfunction="ap_bit_ref<4, true>::operator=(ap_bit_ref<4, true> const&)" off="0" region="0" recursive="0"/>
<pragma file="C:/Xilinx/Vitis_HLS/2023.1/common/technology/autopilot\etc/ap_common.h" line="0" pragmaType="inline" parentfunction="ssdm_int<2, true>::ssdm_int()" off="0" region="0" recursive="0"/>
<pragma file="" line="0" pragmaType="inline" parentfunction="ap_int_base<8, true>& operator^=<8, true>(ap_int_base<8, true>&, unsigned char)" off="0" region="0" recursive="0"/>
<pragma file="" line="0" pragmaType="inline" parentfunction="ap_bit_ref<2, true>::operator=(ap_bit_ref<2, true> const&)" off="0" region="0" recursive="0"/>
<pragma file="" line="0" pragmaType="inline" parentfunction="ap_int_base<8, true>& ap_int_base<8, true>::operator^=<8, false>(ap_int_base<8, false> const&)" off="0" region="0" recursive="0"/>
<pragma file="" line="0" pragmaType="inline" parentfunction="ap_bit_ref<2, true>::operator=(unsigned long long)" off="0" region="0" recursive="0"/>
<pragma file="" line="0" pragmaType="inline" parentfunction="checkOverflowCsim" off="0" region="0" recursive="0"/>
<pragma file="C:/Xilinx/Vitis_HLS/2023.1/common/technology/autopilot\etc/ap_common.h" line="0" pragmaType="inline" parentfunction="ssdm_int<2, false>::ssdm_int()" off="0" region="0" recursive="0"/>
<pragma file="C:/Xilinx/Vitis_HLS/2023.1/common/technology/autopilot\etc/ap_common.h" line="0" pragmaType="inline" parentfunction="ssdm_int<4, false>::ssdm_int()" off="0" region="0" recursive="0"/>
<pragma file="" line="0" pragmaType="inline" parentfunction="checkOverflowBaseC" off="0" region="0" recursive="0"/>
<pragma file="" line="0" pragmaType="inline" parentfunction="checkOverflowCsim" off="0" region="0" recursive="0"/>
<pragma file="" line="0" pragmaType="inline" parentfunction="ap_concat_ref<4, ap_int_base<4, true>, 4, ap_int_base<4, true> >& ap_concat_ref<4, ap_int_base<4, true>, 4, ap_int_base<4, true> >::operator=<8, true>(ap_int_base<8, true> const&)" off="0" region="0" recursive="0"/>
<pragma file="" line="0" pragmaType="inline" parentfunction="ap_bit_ref<8, true>::operator=(bool)" off="0" region="0" recursive="0"/>
<pragma file="C:/Xilinx/Vitis_HLS/2023.1/common/technology/autopilot\etc/ap_common.h" line="0" pragmaType="inline" parentfunction="ssdm_int<8, true>::ssdm_int()" off="0" region="0" recursive="0"/>
<pragma file="" line="0" pragmaType="inline" parentfunction="ap_bit_ref<4, true>::operator=(int)" off="0" region="0" recursive="0"/>
<pragma file="" line="0" pragmaType="inline" parentfunction="length" off="0" region="0" recursive="0"/>
<pragma file="" line="0" pragmaType="inline" parentfunction="ap_concat_ref<2, ap_int_base<2, true>, 2, ap_int_base<2, true> >& ap_concat_ref<2, ap_int_base<2, true>, 2, ap_int_base<2, true> >::operator=<4, true>(ap_int_base<4, true> const&)" off="0" region="0" recursive="0"/>
<pragma file="C:/Xilinx/Vitis_HLS/2023.1/common/technology/autopilot\etc/ap_common.h" line="0" pragmaType="inline" parentfunction="ssdm_int<4, true>::ssdm_int()" off="0" region="0" recursive="0"/>
</pragmas>
